Metadata-Version: 1.1
Name: uberpong
Version: 0.1.0a1
Summary: An Uber-engineered PONG clone
Home-page: https://github.com/axltxl/uberpong
Author: Alejandro Ricoveri
Author-email: alejandroricoveri@gmail.com
License: MIT
Download-URL: https://github.com/axltxl/uberpong/tarball/0.1.0a1
Keywords: games,pong
Platform: UNKNOWN
Classifier: Development Status :: 3 - Alpha
Classifier: Topic :: Games/Entertainment :: Arcade
Classifier: Natural Language :: English
Classifier: License :: OSI Approved :: MIT License
Classifier: Programming Language :: Python
Classifier: Programming Language :: Python :: 3.5
Classifier: Programming Language :: Python :: 3.4
Classifier: Programming Language :: Python :: 3.3
